setup.py
RoCheck/__init__.py
RoCheck.egg-info/PKG-INFO
RoCheck.egg-info/SOURCES.txt
RoCheck.egg-info/dependency_links.txt
RoCheck.egg-info/requires.txt
RoCheck.egg-info/top_level.txt