Metadata-Version: 2.1
Name: RoCheck
Version: 0.2.2
Summary: UNKNOWN
Home-page: UNKNOWN
Author: Kwok6140
Author-email: kwok6140@outlook.com
License: MIT
Platform: UNKNOWN
